ignos/__init__.py
ignos/api/__init__.py
ignos/api/client/__init__.py
ignos/api/client/_client.py
ignos/api/client/_configuration.py
ignos/api/client/_patch.py
ignos/api/client/_serialization.py
ignos/api/client/_version.py
ignos/api/client/py.typed
ignos/api/client/aio/__init__.py
ignos/api/client/aio/_client.py
ignos/api/client/aio/_configuration.py
ignos/api/client/aio/_patch.py
ignos/api/client/aio/operations/__init__.py
ignos/api/client/aio/operations/_operations.py
ignos/api/client/aio/operations/_patch.py
ignos/api/client/models/__init__.py
ignos/api/client/models/_enums.py
ignos/api/client/models/_models.py
ignos/api/client/models/_patch.py
ignos/api/client/operations/__init__.py
ignos/api/client/operations/_operations.py
ignos/api/client/operations/_patch.py
ignos_api_client-2024.5.28.9351.dist-info/METADATA
ignos_api_client-2024.5.28.9351.dist-info/WHEEL
ignos_api_client-2024.5.28.9351.dist-info/top_level.txt
ignos_api_client-2024.5.28.9351.dist-info/RECORD
