Metadata-Version: 2.1
Name: ignos-api-client
Version: 2024.5.28.9351
Summary: ignos-api-client
Home-page: 
Author-email: 
Keywords: azure,azure sdk
Requires-Dist: isodate >=0.6.1
Requires-Dist: azure-core >=1.30.0
